krionis_pipeline-0.9.0.dist-info/licenses/LICENSE
rag_llm_api_pipeline/__init__.py
rag_llm_api_pipeline/config_loader.py
rag_llm_api_pipeline/llm_wrapper.py
rag_llm_api_pipeline/loader.py
rag_llm_api_pipeline/retriever.py
rag_llm_api_pipeline/api/__init__.py
rag_llm_api_pipeline/api/server.py
rag_llm_api_pipeline/cli/__init__.py
rag_llm_api_pipeline/cli/main.py
rag_llm_api_pipeline/web/index.html
krionis_pipeline-0.9.0.dist-info/METADATA
krionis_pipeline-0.9.0.dist-info/WHEEL
krionis_pipeline-0.9.0.dist-info/entry_points.txt
krionis_pipeline-0.9.0.dist-info/top_level.txt
krionis_pipeline-0.9.0.dist-info/RECORD
