Metadata-Version: 2.4
Name: krionis-pipeline
Version: 0.9.0
Summary: Krionis Pipeline - multimodal RAG pipeline for low-compute, local, real-world deployment
Home-page: https://github.com/pkbythebay29/ot-rag-llm-api
Author: pkbythebay29
Author-email: kannan@haztechrisk.org
Project-URL: Homepage, https://pypi.org/project/krionis-pipeline/
Project-URL: Source, https://github.com/pkbythebay29/ot-rag-llm-api
Classifier: Development Status :: 5 - Production/Stable
Classifier: Programming Language :: Python :: 3
Classifier: Programming Language :: Python :: 3 :: Only
Classifier: License :: OSI Approved :: MIT License
Classifier: Operating System :: OS Independent
Classifier: Topic :: Software Development :: Libraries
Classifier: Topic :: Scientific/Engineering :: Artificial Intelligence
Requires-Python: >=3.8
License-File: LICENSE
Requires-Dist: torch>=2.2
Requires-Dist: transformers>=4.42.3
Requires-Dist: accelerate>=0.30.1
Requires-Dist: sentence-transformers>=2.7
Requires-Dist: faiss-cpu>=1.8.0
Requires-Dist: fastapi>=0.111
Requires-Dist: uvicorn[standard]>=0.30
Requires-Dist: pydantic>=2.7
Requires-Dist: pyyaml>=6.0.1
Requires-Dist: pytesseract>=0.3.10
Requires-Dist: pillow>=10.3
Requires-Dist: moviepy==1.0.2
Requires-Dist: pymupdf>=1.24.5
Requires-Dist: openai-harmony>=0.0.3
Requires-Dist: tqdm>=4.66
Requires-Dist: SpeechRecognition>=3.8.1
Requires-Dist: typer>=0.9
Requires-Dist: psutil>=5.9
Dynamic: author
Dynamic: author-email
Dynamic: classifier
Dynamic: description
Dynamic: description-content-type
Dynamic: home-page
Dynamic: license-file
Dynamic: project-url
Dynamic: requires-dist
Dynamic: requires-python
Dynamic: summary
